bubble_text/__init__.py
bubble_text/bubbletext.py
bubble_text-1.0.1.dist-info/LICENCE
bubble_text-1.0.1.dist-info/METADATA
bubble_text-1.0.1.dist-info/WHEEL
bubble_text-1.0.1.dist-info/top_level.txt
bubble_text-1.0.1.dist-info/RECORD
