Metadata-Version: 2.1
Name: bubble-text
Version: 1.0.1
Summary: Styling for colorful bubble text in the command line.
Home-page: https://github.com/tom-draper/bubble-text
Author: Tom Draper
Author-email: Tom Draper <tomjdraper1@gmail.com>
Project-URL: repository, https://github.com/tom-draper/bubble-text
Keywords: cli,text,styling
Classifier: License :: OSI Approved :: MIT License
Classifier: Programming Language :: Python
Classifier: Programming Language :: Python :: 3
Requires-Python: >=3.6
License-File: LICENCE
Requires-Dist: termcolor
Provides-Extra: build
Requires-Dist: build ; extra == 'build'
Requires-Dist: twine ; extra == 'build'
Provides-Extra: dev
Requires-Dist: pytest ; extra == 'dev'
